LICENSE
MANIFEST.in
README.rst
setup.py
django_template_server.egg-info/PKG-INFO
django_template_server.egg-info/SOURCES.txt
django_template_server.egg-info/dependency_links.txt
django_template_server.egg-info/entry_points.txt
django_template_server.egg-info/not-zip-safe
django_template_server.egg-info/requires.txt
django_template_server.egg-info/top_level.txt
templateserver/__init__.py
templateserver/maketemplateserver.py
templateserver/runserver_template.py