Metadata-Version: 1.0
Name: django-template-server
Version: 0.3.1
Summary: Makes it easy to test Django templates
Home-page: http://github.com/ojii/django-template-server
Author: Jonas Obrist
Author-email: jonas.obrist@divio.ch
License: BSD
Keywords: django templates
Platform: UNKNOWN
Classifier: Development Status :: 4 - Beta
Classifier: Intended Audience :: Developers
Classifier: License :: OSI Approved :: BSD License
Classifier: Topic :: Software Development
Classifier: Programming Language :: Python :: 2
Classifier: Programming Language :: Python :: 2.7
